Metadata-Version: 2.1
Name: odoo14-addon-pos_analytic_by_config
Version: 14.0.1.0.1.dev15
Summary: Use analytic account defined on POS configuration for POS orders
Home-page: https://github.com/OCA/account-analytic
Author: ACSONE SA/NV, Tecnativa, Odoo Community Association (OCA)
Author-email: support@odoo-community.org
License: AGPL-3
Classifier: Programming Language :: Python
Classifier: Framework :: Odoo
Classifier: Framework :: Odoo :: 14.0
Classifier: License :: OSI Approved :: GNU Affero General Public License v3
Requires-Python: >=3.6
Requires-Dist: odoo<14.1dev,>=14.0a
